q2gui/__init__.py
q2gui/__main__.py
q2gui/i18n.py
q2gui/locale/de/de.po
q2gui/locale/de/de.po~
q2gui/locale/de/LC_MESSAGES/q2gui.mo
q2gui/locale/q2gui.pot
q2gui/locale/ru/LC_MESSAGES/q2gui.mo
q2gui/locale/ru/ru.po
q2gui/locale/ru/ru.po~
q2gui/pyqt6/__init__.py
q2gui/pyqt6/q2app.py
q2gui/pyqt6/q2form.py
q2gui/pyqt6/q2model.py
q2gui/pyqt6/q2style.py
q2gui/pyqt6/q2widget.py
q2gui/pyqt6/q2window.py
q2gui/pyqt6/widgets/__init__.py
q2gui/pyqt6/widgets/q2button.py
q2gui/pyqt6/widgets/q2check.py
q2gui/pyqt6/widgets/q2code.py
q2gui/pyqt6/widgets/q2color.py
q2gui/pyqt6/widgets/q2combo.py
q2gui/pyqt6/widgets/q2date.py
q2gui/pyqt6/widgets/q2doublespin.py
q2gui/pyqt6/widgets/q2frame.py
q2gui/pyqt6/widgets/q2grid.py
q2gui/pyqt6/widgets/q2image.py
q2gui/pyqt6/widgets/q2label.py
q2gui/pyqt6/widgets/q2line.py
q2gui/pyqt6/widgets/q2list.py
q2gui/pyqt6/widgets/q2lookup.py
q2gui/pyqt6/widgets/q2progressbar.py
q2gui/pyqt6/widgets/q2radio.py
q2gui/pyqt6/widgets/q2relation.py
q2gui/pyqt6/widgets/q2scroller.py
q2gui/pyqt6/widgets/q2sheet.py
q2gui/pyqt6/widgets/q2space.py
q2gui/pyqt6/widgets/q2spin.py
q2gui/pyqt6/widgets/q2tab.py
q2gui/pyqt6/widgets/q2text.py
q2gui/pyqt6/widgets/q2time.py
q2gui/pyqt6/widgets/q2toolbar.py
q2gui/pyqt6/widgets/q2toolbutton.py
q2gui/q2app.py
q2gui/q2dialogs.py
q2gui/q2form.py
q2gui/q2icons.py
q2gui/q2model.py
q2gui/q2style.py
q2gui/q2utils.py
q2gui/q2widget.py
q2gui/q2window.py
q2gui/version.py
q2gui-0.1.204.dist-info/LICENSE
q2gui-0.1.204.dist-info/METADATA
q2gui-0.1.204.dist-info/WHEEL
q2gui-0.1.204.dist-info/RECORD
