Metadata-Version: 2.1
Name: q2gui
Version: 0.1.204
Summary: Python GUI toolkit
License: Apache 2.0
Author: Andrei Puchko
Author-email: andrei.puchko@gmx.de
Requires-Python: >=3.8.1
Classifier: License :: Other/Proprietary License
Classifier: Programming Language :: Python :: 3
Classifier: Programming Language :: Python :: 3.9
Classifier: Programming Language :: Python :: 3.10
Classifier: Programming Language :: Python :: 3.11
Requires-Dist: PyQt6 (>=6.3,<6.6)
Requires-Dist: PyQt6-QScintilla (>=2.13.3,<3.0.0)
Requires-Dist: PyQt6-Qt6 (>=6.3,<6.6)
Requires-Dist: darkdetect (>=0.8.0,<0.9.0)
Requires-Dist: q2db (>=0.1.28)
